pycounts_gthrm/__init__.py
pycounts_gthrm/plotting.py
pycounts_gthrm/pycounts_gthrm.py
pycounts_gthrm-0.1.0.dist-info/LICENSE
pycounts_gthrm-0.1.0.dist-info/WHEEL
pycounts_gthrm-0.1.0.dist-info/METADATA
pycounts_gthrm-0.1.0.dist-info/RECORD
