Metadata-Version: 2.1
Name: pycounts-gthrm
Version: 0.1.0
Summary: calculate word counts in a text file
License: MIT
Author: Thulasiram Gunipati
Requires-Python: >=3.9
Classifier: License :: OSI Approved :: MIT License
Classifier: Programming Language :: Python :: 3
Classifier: Programming Language :: Python :: 3.10
Classifier: Programming Language :: Python :: 3.9
Requires-Dist: matplotlib (>=3.6.3)
